<?xml version="1.0" encoding="UTF-8"?>
<?xml-model href="https://raw.githubusercontent.com/rudnerbjoern/iTop-schema/refs/heads/main/3.2/itop_design.xsd"?>
<itop_design xmlns:xsi="http://www.w3.org/2001/XMLSchema-instance" version="3.2">
    <!--
    * @copyright   Copyright (C) 2024 Björn Rudner
    * @license     https://www.gnu.org/licenses/gpl-3.0.en.html
    -->
    <classes>
        <class id="Workstation" _delta="if_exists">
            <presentation>
                <details>
                    <items>
                        <item id="col:col2" _delta="must_exist">
                            <items>
                                <item id="fieldset:Server:otherinfo" _delta="must_exist">
                                    <items>
                                        <item id="costcenter_id" _delta="define">
                                            <rank>5</rank>
                                        </item>
                                    </items>
                                </item>
                            </items>
                        </item>
                    </items>
                </details>
                <search>
                    <items>
                        <item id="costcenter_id" _delta="define">
                            <rank>140</rank>
                        </item>
                    </items>
                </search>
            </presentation>
        </class>
        <class id="DockingStation" _delta="if_exists">
            <presentation>
                <details>
                    <items>
                        <item id="col:col2" _delta="must_exist">
                            <items>
                                <item id="fieldset:Server:otherinfo" _delta="must_exist">
                                    <items>
                                        <item id="costcenter_id" _delta="define">
                                            <rank>5</rank>
                                        </item>
                                    </items>
                                </item>
                            </items>
                        </item>
                    </items>
                </details>
                <search>
                    <items>
                        <item id="costcenter_id" _delta="define">
                            <rank>140</rank>
                        </item>
                    </items>
                </search>
            </presentation>
        </class>
        <class id="Monitor" _delta="if_exists">
            <presentation>
                <details>
                    <items>
                        <item id="col:col2" _delta="must_exist">
                            <items>
                                <item id="fieldset:Server:otherinfo" _delta="must_exist">
                                    <items>
                                        <item id="costcenter_id" _delta="define">
                                            <rank>5</rank>
                                        </item>
                                    </items>
                                </item>
                            </items>
                        </item>
                    </items>
                </details>
                <search>
                    <items>
                        <item id="costcenter_id" _delta="define">
                            <rank>140</rank>
                        </item>
                    </items>
                </search>
            </presentation>
        </class>
        <class id="Keyboard" _delta="if_exists">
            <presentation>
                <details>
                    <items>
                        <item id="col:col2" _delta="must_exist">
                            <items>
                                <item id="fieldset:Server:otherinfo" _delta="must_exist">
                                    <items>
                                        <item id="costcenter_id" _delta="define">
                                            <rank>5</rank>
                                        </item>
                                    </items>
                                </item>
                            </items>
                        </item>
                    </items>
                </details>
                <search>
                    <items>
                        <item id="costcenter_id" _delta="define">
                            <rank>140</rank>
                        </item>
                    </items>
                </search>
            </presentation>
        </class>
        <class id="Mouse" _delta="if_exists">
            <presentation>
                <details>
                    <items>
                        <item id="col:col2" _delta="must_exist">
                            <items>
                                <item id="fieldset:Server:otherinfo" _delta="must_exist">
                                    <items>
                                        <item id="costcenter_id" _delta="define">
                                            <rank>5</rank>
                                        </item>
                                    </items>
                                </item>
                            </items>
                        </item>
                    </items>
                </details>
                <search>
                    <items>
                        <item id="costcenter_id" _delta="define">
                            <rank>140</rank>
                        </item>
                    </items>
                </search>
            </presentation>
        </class>
        <class id="Headset" _delta="if_exists">
            <presentation>
                <details>
                    <items>
                        <item id="col:col2" _delta="must_exist">
                            <items>
                                <item id="fieldset:Server:otherinfo" _delta="must_exist">
                                    <items>
                                        <item id="costcenter_id" _delta="define">
                                            <rank>5</rank>
                                        </item>
                                    </items>
                                </item>
                            </items>
                        </item>
                    </items>
                </details>
                <search>
                    <items>
                        <item id="costcenter_id" _delta="define">
                            <rank>140</rank>
                        </item>
                    </items>
                </search>
            </presentation>
        </class>
        <class id="Scanner" _delta="if_exists">
            <presentation>
                <details>
                    <items>
                        <item id="col:col2" _delta="must_exist">
                            <items>
                                <item id="fieldset:Server:otherinfo" _delta="must_exist">
                                    <items>
                                        <item id="costcenter_id" _delta="define">
                                            <rank>5</rank>
                                        </item>
                                    </items>
                                </item>
                            </items>
                        </item>
                    </items>
                </details>
                <search>
                    <items>
                        <item id="costcenter_id" _delta="define">
                            <rank>140</rank>
                        </item>
                    </items>
                </search>
            </presentation>
        </class>
        <class id="BarcodeScanner" _delta="if_exists">
            <presentation>
                <details>
                    <items>
                        <item id="col:col2" _delta="must_exist">
                            <items>
                                <item id="fieldset:Server:otherinfo" _delta="must_exist">
                                    <items>
                                        <item id="costcenter_id" _delta="define">
                                            <rank>5</rank>
                                        </item>
                                    </items>
                                </item>
                            </items>
                        </item>
                    </items>
                </details>
                <search>
                    <items>
                        <item id="costcenter_id" _delta="define">
                            <rank>140</rank>
                        </item>
                    </items>
                </search>
            </presentation>
        </class>
        <class id="ConferenceSystem" _delta="if_exists">
            <presentation>
                <details>
                    <items>
                        <item id="col:col2" _delta="must_exist">
                            <items>
                                <item id="fieldset:Server:otherinfo" _delta="must_exist">
                                    <items>
                                        <item id="costcenter_id" _delta="define">
                                            <rank>5</rank>
                                        </item>
                                    </items>
                                </item>
                            </items>
                        </item>
                    </items>
                </details>
                <search>
                    <items>
                        <item id="costcenter_id" _delta="define">
                            <rank>140</rank>
                        </item>
                    </items>
                </search>
            </presentation>
        </class>
        <class id="MobilePhone" _delta="if_exists">
            <presentation>
                <details>
                    <items>
                        <item id="costcenter_id" _delta="delete_if_exists" />
                        <item id="col:col2" _delta="must_exist">
                            <items>
                                <item id="fieldset:Server:otherinfo" _delta="must_exist">
                                    <items>
                                        <item id="costcenter_id" _delta="define">
                                            <rank>5</rank>
                                        </item>
                                    </items>
                                </item>
                            </items>
                        </item>
                    </items>
                </details>
                <search>
                    <items>
                        <item id="costcenter_id" _delta="delete_if_exists" />
                        <item id="costcenter_id" _delta="define">
                            <rank>160</rank>
                        </item>
                    </items>
                </search>
            </presentation>
        </class>
        <class id="IPPhone" _delta="if_exists">
            <presentation>
                <details>
                    <items>
                        <item id="costcenter_id" _delta="delete_if_exists" />
                        <item id="col:col2" _delta="must_exist">
                            <items>
                                <item id="fieldset:Server:otherinfo" _delta="must_exist">
                                    <items>
                                        <item id="costcenter_id" _delta="define">
                                            <rank>5</rank>
                                        </item>
                                    </items>
                                </item>
                            </items>
                        </item>
                    </items>
                </details>
                <search>
                    <items>
                        <item id="costcenter_id" _delta="delete_if_exists" />
                        <item id="costcenter_id" _delta="define">
                            <rank>140</rank>
                        </item>
                    </items>
                </search>
            </presentation>
        </class>
    </classes>
    <menus>
        <menu id="EndUserSpace" xsi:type="DashboardMenuNode" _delta="must_exist">
            <definition>
                <cells>
                    <cell id="peripherals-900" _delta="must_exist">
                        <dashlets>
                            <dashlet id="peripherals-912" xsi:type="DashletBadge" _delta="define">
                                <rank>12</rank>
                                <class>CostCenter</class>
                            </dashlet>
                        </dashlets>
                    </cell>
                </cells>
            </definition>
        </menu>
    </menus>
    <module_parameters>
        <parameters id="br-peripherals" _delta="must_exist">
            <!-- update CostCenter of linked peripherals to the CostCenter of the workstation -->
            <update_costcenters_from_workstation type="bool" _delta="define">true</update_costcenters_from_workstation>
        </parameters>
    </module_parameters>
</itop_design>
